twarc_network/__init__.py
twarc_network/index.html
twarc_network-0.1.1.dist-info/LICENSE
twarc_network-0.1.1.dist-info/METADATA
twarc_network-0.1.1.dist-info/WHEEL
twarc_network-0.1.1.dist-info/entry_points.txt
twarc_network-0.1.1.dist-info/top_level.txt
twarc_network-0.1.1.dist-info/RECORD
