Metadata-Version: 2.1
Name: twarc-network
Version: 0.1.1
Summary: Generate network visualizations for Twitter data
Home-page: https://github.com/docnow/twarc-network
Author: Ed Summers
Author-email: ehs@pobox.com
License: MIT
Classifier: License :: OSI Approved :: MIT License
Requires-Python: >=3.3
License-File: LICENSE
Requires-Dist: twarc
Requires-Dist: networkx
Requires-Dist: pydot
